poliastro/__init__.py
poliastro/bodies.py
poliastro/ephem.py
poliastro/examples.py
poliastro/maneuver.py
poliastro/spheroid_location.py
poliastro/util.py
poliastro/warnings.py
poliastro/constants/__init__.py
poliastro/constants/general.py
poliastro/constants/rotational_elements.py
poliastro/core/__init__.py
poliastro/core/angles.py
poliastro/core/czml_utils.py
poliastro/core/elements.py
poliastro/core/events.py
poliastro/core/fixed.py
poliastro/core/flybys.py
poliastro/core/hyper.py
poliastro/core/iod.py
poliastro/core/maneuver.py
poliastro/core/perturbations.py
poliastro/core/sensors.py
poliastro/core/spheroid_location.py
poliastro/core/stumpff.py
poliastro/core/util.py
poliastro/core/earth_atmosphere/__init__.py
poliastro/core/earth_atmosphere/jacchia.py
poliastro/core/earth_atmosphere/util.py
poliastro/core/propagation/__init__.py
poliastro/core/propagation/farnocchia.py
poliastro/core/thrust/__init__.py
poliastro/core/thrust/change_a_inc.py
poliastro/core/thrust/change_argp.py
poliastro/core/thrust/change_ecc_inc.py
poliastro/core/thrust/change_ecc_quasioptimal.py
poliastro/czml/__init__.py
poliastro/czml/extract_czml.py
poliastro/earth/__init__.py
poliastro/earth/enums.py
poliastro/earth/sensors.py
poliastro/earth/atmosphere/__init__.py
poliastro/earth/atmosphere/base.py
poliastro/earth/atmosphere/coesa62.py
poliastro/earth/atmosphere/coesa76.py
poliastro/earth/atmosphere/jacchia.py
poliastro/earth/atmosphere/data/coesa62.dat
poliastro/earth/atmosphere/data/coesa76.dat
poliastro/earth/atmosphere/data/coesa76_p.dat
poliastro/earth/atmosphere/data/coesa76_rho.dat
poliastro/earth/plotting/__init__.py
poliastro/earth/plotting/groundtrack.py
poliastro/earth/plotting/utils.py
poliastro/frames/__init__.py
poliastro/frames/ecliptic.py
poliastro/frames/enums.py
poliastro/frames/equatorial.py
poliastro/frames/fixed.py
poliastro/frames/util.py
poliastro/iod/__init__.py
poliastro/iod/izzo.py
poliastro/iod/vallado.py
poliastro/plotting/__init__.py
poliastro-0.16.3.dist-info/COPYING
poliastro-0.16.3.dist-info/WHEEL
poliastro-0.16.3.dist-info/METADATA
poliastro-0.16.3.dist-info/RECORD
