Metadata-Version: 2.1
Name: poliastro
Version: 0.16.3
Summary: Utilities and Python wrappers for Orbital Mechanics
Keywords: aero,aerospace,engineering,astrodynamics,orbits,kepler,orbital mechanics
Author-email: Juan Luis Cano Rodríguez <hello@juanlu.space>
Requires-Python: >=3.8,<3.11
Classifier: License :: OSI Approved :: MIT License
Classifier: Development Status :: 4 - Beta
Classifier: Intended Audience :: Education
Classifier: Intended Audience :: Science/Research
Classifier: License :: OSI Approved :: MIT License
Classifier: Operating System :: OS Independent
Classifier: Programming Language :: Python
Classifier: Programming Language :: Python :: 3
Classifier: Programming Language :: Python :: 3.8
Classifier: Programming Language :: Python :: 3.9
Classifier: Programming Language :: Python :: 3.10
Classifier: Programming Language :: Python :: Implementation :: CPython
Classifier: Topic :: Scientific/Engineering
Classifier: Topic :: Scientific/Engineering :: Physics
Classifier: Topic :: Scientific/Engineering :: Astronomy
Requires-Dist: astropy >=3.2,<6
Requires-Dist: astroquery >=0.3.9
Requires-Dist: cached_property ; python_version<'3.8'
Requires-Dist: jplephem
Requires-Dist: matplotlib >=2.0,!=3.0.1
Requires-Dist: numba >=0.46 ; python_version<'3.9'
Requires-Dist: numba >=0.53.0 ; python_version>='3.9'
Requires-Dist: numpy
Requires-Dist: pandas
Requires-Dist: plotly >=4.0,<6
Requires-Dist: pyerfa
Requires-Dist: scipy >=1.4.0
Requires-Dist: czml3 ~=0.5.3 ; extra == "cesium"
Requires-Dist: httpx ; extra == "doc"
Requires-Dist: ipython>=5.0 ; extra == "doc"
Requires-Dist: ipywidgets>=7.6 ; extra == "doc"
Requires-Dist: jupyter-client ; extra == "doc"
Requires-Dist: jupytext ; extra == "doc"
Requires-Dist: myst-parser>=0.13.1 ; extra == "doc"
Requires-Dist: nbsphinx>=0.8.6 ; extra == "doc"
Requires-Dist: nbconvert>=5.5 ; extra == "doc"
Requires-Dist: sgp4 ; extra == "doc"
Requires-Dist: sphinx!=3.5,!=4.0 ; extra == "doc"
Requires-Dist: sphinx-autoapi ; extra == "doc"
Requires-Dist: sphinx-gallery<=0.7.0 ; extra == "doc"
Requires-Dist: sphinx_rtd_theme~=1.0.0 ; extra == "doc"
Requires-Dist: sphinx-hoverxref==0.7b1 ; extra == "doc"
Requires-Dist: sphinx-notfound-page ; extra == "doc"
Requires-Dist: sphinx-copybutton>0.2.9 ; extra == "doc"
Requires-Dist: sphinx-github-role~=0.1.0 ; extra == "doc"
Requires-Dist: notebook ; extra == "jupyter"
Requires-Dist: ipywidgets>=7.6 ; extra == "jupyter"
Requires-Dist: coverage ; extra == "test"
Requires-Dist: hypothesis ; extra == "test"
Requires-Dist: import-linter[toml] ; extra == "test"
Requires-Dist: mypy>=0.740 ; extra == "test"
Requires-Dist: pre-commit ; extra == "test"
Requires-Dist: pytest>=3.2 ; extra == "test"
Requires-Dist: pytest-cov<2.6.0 ; extra == "test"
Requires-Dist: pytest-doctestplus>=0.8 ; extra == "test"
Requires-Dist: pytest-mpl ; extra == "test"
Requires-Dist: pytest-mypy ; extra == "test"
Requires-Dist: pytest-remotedata ; extra == "test"
Project-URL: Documentation, https://docs.poliastro.space
Project-URL: Funding, https://opencollective.com/poliastro
Project-URL: Homepage, https://www.poliastro.space
Project-URL: Source, https://github.com/poliastro/poliastro
Project-URL: Tracker, https://github.com/poliastro/poliastro/issues
Provides-Extra: cesium
Provides-Extra: doc
Provides-Extra: jupyter
Provides-Extra: test
